ashraf_camera/__init__.py
ashraf_camera/camera.py
ashraf_camera-1.0.0.dist-info/METADATA
ashraf_camera-1.0.0.dist-info/WHEEL
ashraf_camera-1.0.0.dist-info/top_level.txt
ashraf_camera-1.0.0.dist-info/RECORD
