Metadata-Version: 2.4
Name: ashraf-camera
Version: 1.0.0
Summary: Library to take screenshots or photos using simple commands
Author: Ashraf
Requires-Python: >=3.7
Requires-Dist: opencv-python
Requires-Dist: pyautogui
Dynamic: author
Dynamic: requires-dist
Dynamic: requires-python
Dynamic: summary
